CHANGES.txt
DEVELOPMENT.txt
README.rst
bootstrap.py
buildout.cfg
setup.py
docs/LICENSE.GPL
docs/LICENSE.txt
experimental/__init__.py
experimental.btree.egg-info/PKG-INFO
experimental.btree.egg-info/SOURCES.txt
experimental.btree.egg-info/dependency_links.txt
experimental.btree.egg-info/entry_points.txt
experimental.btree.egg-info/namespace_packages.txt
experimental.btree.egg-info/not-zip-safe
experimental.btree.egg-info/requires.txt
experimental.btree.egg-info/top_level.txt
experimental/btree/__init__.py
experimental/btree/configure.zcml
experimental/btree/difference.c
experimental/btree/difference.pyx
experimental/btree/intersection.c
experimental/btree/intersection.pyx
experimental/btree/setpatches.py
experimental/btree/tests/__init__.py
experimental/btree/tests/test_performance.py
experimental/btree/tests/test_sets.py