Metadata-Version: 1.0
Name: experimental.btree
Version: 1.1
Summary: ZODB BTree optimizations
Home-page: http://www.jarn.com/
Author: Jarn AS
Author-email: info@jarn.com
License: GPL
Keywords: plone zodb btree
Platform: UNKNOWN
Classifier: Framework :: Plone
Classifier: Programming Language :: Python
Classifier: Programming Language :: Python :: 2.6
Classifier: Programming Language :: Python :: 2.7
